Metadata-Version: 1.0
Name: setuptools-flakes
Version: 0.1
Summary: Setup tools command for pyflakes
Home-page: https://github.com/johnnoone/setuptools-pyflakes.git
Author: Xavier Barbosa
Author-email: UNKNOWN
License: BSD
Keywords: setuptools pyflakes
Platform: UNKNOWN
Classifier: Topic :: Documentation
Classifier: Framework :: Setuptools Plugin
Classifier: Development Status :: 4 - Beta
Classifier: Programming Language :: Python
Classifier: Intended Audience :: Developers
Classifier: Operating System :: OS Independent
Classifier: License :: OSI Approved :: BSD License
Classifier: Topic :: Software Development :: Documentation
Classifier: Topic :: Software Development :: Libraries :: Python Modules
